pycx3/__init__.py
pycx3/__main__.py
pycx3/cli.py
pycx3/compile.py
pycx3-1.0.3.dist-info/LICENSE
pycx3-1.0.3.dist-info/METADATA
pycx3-1.0.3.dist-info/WHEEL
pycx3-1.0.3.dist-info/entry_points.txt
pycx3-1.0.3.dist-info/top_level.txt
pycx3-1.0.3.dist-info/RECORD
