Metadata-Version: 2.1
Name: pycx3
Version: 1.0.3
Summary: Compiler Python version 3 source file to binary
Home-page: https://github.com/FajarKim/pycx3
Author: Rangga Fajar Oktariansyah
Author-email: fajarrkim@gmail.com
License: AGPL-3.0
Project-URL: Documentation, https://github.com/FajarKim/pycx3#readme
Project-URL: Donate, https://buymeacoffee.com/fajarkim
Project-URL: Source Code, https://github.com/FajarKim/pycx3
Project-URL: Bug Tracker, https://github.com/FajarKim/pycx3/issues
Keywords: python2 cython compiler performance legacy
Platform: UNKNOWN
Classifier: Development Status :: 4 - Beta
Classifier: Environment :: Console
Classifier: Intended Audience :: Developers
Classifier: License :: OSI Approved :: GNU Affero General Public License v3
Classifier: Programming Language :: Python
Classifier: Programming Language :: Python :: 3
Classifier: Programming Language :: Python :: 3 :: Only
Classifier: Programming Language :: Python :: 3.8
Classifier: Programming Language :: Python :: 3.9
Classifier: Programming Language :: Python :: 3.10
Classifier: Programming Language :: Python :: 3.11
Classifier: Operating System :: OS Independent
Classifier: Topic :: Software Development :: Compilers
Classifier: Topic :: Software Development :: Libraries :: Python Modules
Requires-Python: >=3.8
Requires-Dist: Cython >=0.29.34
